MANIFEST.in
README.rst
setup.py
hpo_downloader/__init__.py
hpo_downloader/__version__.py
hpo_downloader/mapping.py
hpo_downloader.egg-info/PKG-INFO
hpo_downloader.egg-info/SOURCES.txt
hpo_downloader.egg-info/dependency_links.txt
hpo_downloader.egg-info/requires.txt
hpo_downloader.egg-info/top_level.txt
hpo_downloader/cafa4/__init__.py
hpo_downloader/cafa4/cafa4_mapping.py
hpo_downloader/hpo/__init__.py
hpo_downloader/hpo/hpo_mapping.py
hpo_downloader/uniprot/__init__.py
hpo_downloader/uniprot/uniprot_mapping.py
hpo_downloader/utils/__init__.py
hpo_downloader/utils/non_unique_mapping.py
hpo_downloader/utils/overlap.py