Metadata-Version: 2.1
Name: hpo-downloader
Version: 1.1.0
Summary: Python package to download HPO annotations and mapping to Uniprot ID and AC and CAFA4 IDs.
Home-page: https://github.com/LucaCappelletti94/hpo_downloader
Author: Luca Cappelletti
Author-email: cappelletti.luca94@gmail.com
License: MIT
Platform: UNKNOWN
Classifier: Development Status :: 3 - Alpha
Classifier: License :: OSI Approved :: MIT License
Classifier: Programming Language :: Python :: 3
Provides-Extra: test
